statsapi/__init__.py
statsapi/endpoints.py
statsapi/version.py
tests/__init__.py
tests/test_get.py
MLB_StatsAPI-1.8.dist-info/LICENSE
MLB_StatsAPI-1.8.dist-info/METADATA
MLB_StatsAPI-1.8.dist-info/WHEEL
MLB_StatsAPI-1.8.dist-info/top_level.txt
MLB_StatsAPI-1.8.dist-info/RECORD
