Metadata-Version: 2.1
Name: MLB-StatsAPI
Version: 1.8
Summary: MLB Stats API Wrapper for Python
Home-page: https://github.com/toddrob99/MLB-StatsAPI
Author: Todd Roberts
Author-email: todd@toddrob.com
Classifier: Programming Language :: Python
Classifier: Programming Language :: Python :: 3
Classifier: License :: OSI Approved :: GNU General Public License v3 (GPLv3)
Classifier: Operating System :: OS Independent
License-File: LICENSE
Requires-Dist: requests
